LICENSE
MANIFEST.in
README.md
pyproject.toml
src/millenniumdb_driver/__init__.py
src/millenniumdb_driver/catalog.py
src/millenniumdb_driver/chunk_decoder.py
src/millenniumdb_driver/driver.py
src/millenniumdb_driver/graph_objects.py
src/millenniumdb_driver/iobuffer.py
src/millenniumdb_driver/message_decoder.py
src/millenniumdb_driver/message_receiver.py
src/millenniumdb_driver/millenniumdb_error.py
src/millenniumdb_driver/protocol.py
src/millenniumdb_driver/record.py
src/millenniumdb_driver/request_buffer.py
src/millenniumdb_driver/request_writer.py
src/millenniumdb_driver/response_handler.py
src/millenniumdb_driver/result.py
src/millenniumdb_driver/session.py
src/millenniumdb_driver/websocket_connection.py