Metadata-Version: 2.4
Name: millenniumdb_driver
Version: 1.2.0
Summary: The official MillenniumDB driver for Python
Author-email: Vicente Calisto <vecalisto@uc.cl>, Matías Maldonado <matiasmaldonado@uc.cl>
License-Expression: MIT
Project-URL: Homepage, https://github.com/MillenniumDB/MillenniumDB-driver-python
Project-URL: Bug Tracker, https://github.com/MillenniumDB/MillenniumDB-driver-python/issues
Classifier: Development Status :: 3 - Alpha
Classifier: Intended Audience :: Developers
Classifier: Programming Language :: Python :: 3
Classifier: Operating System :: OS Independent
Requires-Python: >=3.9
License-File: LICENSE
Requires-Dist: numpy
Requires-Dist: pandas
Requires-Dist: websocket-client
Dynamic: license-file
